{
  "category": "geometry",
  "search_keywords": [
    "polygon-create"
  ],
  "description": "Create a polygon in the current geometry set. If the set keyword is given then the edge is created in that set. A list of edges, a list of nodes or a list of points in space can be input. If an edge list is used, the edges must be given in order and form a closed polygon. If a node list is used, edges are created if none are found, and the polygon is automatically closed. If a position list is used, nodes and edges are created if none are found, and the polygon is automatically closed. A warning results if the polygon is not planar or is not convex. If an extrude vector is provided, then the polygon will be extruded along that vector, resulting in a closed volume of polygonal surfaces.",
  "notes": [],
  "python_sdk_alternative": {
    "available": false,
    "workaround": ""
  },
  "versions": {
    "6.0": {
      "command": "geometry polygon create",
      "syntax": "geometry polygon create keyword ...",
      "keywords": [
        {
          "name": "by-edges",
          "syntax": "by-edges <i1><i2>[keyword]",
          "description": "List of edge IDs that belong to the polygon. The IDs must be ordered such that the edges form a closed polygon."
        },
        {
          "name": "by-nodes",
          "syntax": "by-nodes <i1><i2>[keyword]",
          "description": "List of node IDs that belong to the polygon. Edges are created if none are found, and the polygon is automatically closed."
        },
        {
          "name": "by-positions",
          "syntax": "by-positions <v1><v2>[keyword]",
          "description": "List of nodal positions that belong to the polygon. Nodes and edges are created if none are found, and the polygon is automatically closed."
        },
        {
          "name": "extrude",
          "syntax": "extrude <v>",
          "description": "will create polygon and “extrude” in the direction supplied."
        },
        {
          "name": "extra",
          "syntax": "extra <i>a",
          "description": "Optionally assign the extra variable a to index i ."
        },
        {
          "name": "group",
          "syntax": "group <s1>[slot <s2>]",
          "description": "Optionally assign the group name s1 to slot s2 (optional)."
        }
      ],
      "examples": []
    },
    "7.0": {
      "command": "geometry polygon create",
      "syntax": "geometry polygon create keyword ...",
      "keywords": [
        {
          "name": "by-edges",
          "syntax": "by-edges <i1><i2>...",
          "description": "List of edge IDs that belong to the polygon. The IDs must be ordered such that the edges form a closed polygon."
        },
        {
          "name": "by-nodes",
          "syntax": "by-nodes <i1><i2>...",
          "description": "List of node IDs that belong to the polygon. Edges are created if none are found, and the polygon is automatically closed."
        },
        {
          "name": "by-positions",
          "syntax": "by-positions <v1><v2>...",
          "description": "List of nodal positions that belong to the polygon. Nodes and edges are created if none are found, and the polygon is automatically closed."
        },
        {
          "name": "set",
          "syntax": "set <s>",
          "description": "Create the polygon in the set s ."
        },
        {
          "name": "kwd:extrude",
          "syntax": "extrude <v>",
          "description": "will create polygon and “extrude” in the direction supplied."
        },
        {
          "name": "kwd:extra",
          "syntax": "extra <i><a>",
          "description": "Optionally assign the extra variable a to index i ."
        },
        {
          "name": "kwd:group",
          "syntax": "group <s1>[slot <s2>]",
          "description": "Optionally assign the group name s1 to slot s2 (optional)."
        }
      ],
      "examples": []
    },
    "9.0": {
      "command": "geometry polygon create",
      "syntax": "geometry polygon create keyword ...",
      "keywords": [
        {
          "name": "by-edges",
          "syntax": "by-edges <i1><i2>... [polycreateoptions]",
          "description": "List of edge IDs that belong to the polygon. The IDs must be ordered such that the edges form a closed polygon."
        },
        {
          "name": "by-nodes",
          "syntax": "by-nodes <i1><i2>... [polycreateoptions]",
          "description": "List of node IDs that belong to the polygon. Edges are created if none are found, and the polygon is automatically closed."
        },
        {
          "name": "by-positions",
          "syntax": "by-positions <v1><v2>... [polycreateoptions]",
          "description": "List of nodal positions that belong to the polygon. Nodes and edges are created if none are found, and the polygon is automatically closed."
        },
        {
          "name": "set",
          "syntax": "set <s>",
          "description": "Create the polygon in the set s ."
        },
        {
          "name": "kwd:extrude",
          "syntax": "extrude <v>",
          "description": "will create polygon and “extrude” in the direction supplied."
        },
        {
          "name": "kwd:extra",
          "syntax": "extra <i><a>",
          "description": "Optionally assign the extra variable a to index i ."
        },
        {
          "name": "kwd:group",
          "syntax": "group <s1>[slot <s2>]",
          "description": "Optionally assign the group name s1 to slot s2 (optional)."
        }
      ],
      "examples": []
    }
  }
}
