{
  "category": "extruder",
  "search_keywords": [
    "path",
    "extrude",
    "mode",
    "sketch",
    "extrude-mode"
  ],
  "description": "Set the extrude-mode",
  "python_sdk_alternative": {
    "available": false
  },
  "versions": {
    "9.0": {
      "command": "sketch path extrude-mode",
      "syntax": "sketch path extrude-mode keyword",
      "keywords": [
        {
          "name": "parallel",
          "syntax": "parallel",
          "description": "Keep cross-sections parallel to the construction plane."
        },
        {
          "name": "perpendicular",
          "syntax": "perpendicular",
          "description": "Keep cross-sections perpendicular to the extrusion path and constant in size."
        },
        {
          "name": "adjusted",
          "syntax": "adjusted",
          "description": "Keep rotated cross-sections (adjusted to the next segment) and constant in size."
        }
      ]
    }
  }
}
