{
  "name": "wall",
  "item_type": "wall",
  "search_keywords": ["wall", "boundary", "transparency", "color", "force"],
  "description": "Configuration keywords for 'plot item create wall'. Controls wall rendering, transparency, coloring by attributes, cut planes, and legend display.",
  "base_syntax": "plot item create wall <keywords...>",

  "basic_keywords": [
    {
      "keyword": "active on",
      "description": "Show item in plot (default when created)",
      "syntax": "active on"
    },
    {
      "keyword": "active off",
      "description": "Hide item without removing it",
      "syntax": "active off"
    },
    {
      "keyword": "transparency",
      "description": "Set wall transparency level (0 = opaque, 100 = fully transparent)",
      "syntax": "transparency <0-100>",
      "notes": "Typical value: 70 for semi-transparent walls"
    },
    {
      "keyword": "legend active on",
      "description": "Show color legend for this item",
      "syntax": "legend active on"
    },
    {
      "keyword": "color-options",
      "description": "Configure color scale for numeric/vector attributes",
      "syntax": "color-options scaled ramp rainbow minimum automatic maximum automatic"
    }
  ],

  "sub_items": [
    {
      "name": "color-by",
      "file": "color-by.json",
      "description": "Color walls by vector or text attributes (force-contact, group, name, etc.)"
    },
    {
      "name": "cut",
      "file": "cut.json",
      "description": "Clip visualization with a cutting plane"
    }
  ],

  "common_usage_patterns": [
    {
      "use_case": "Semi-transparent walls",
      "command": "plot item create wall active on transparency 70",
      "description": "Default wall visualization with 70% transparency"
    },
    {
      "use_case": "Walls colored by contact force",
      "command": "plot item create wall active on color-by vector-attribute \"force-contact\" color-options scaled ramp rainbow minimum automatic maximum automatic transparency 50 legend active on",
      "description": "Force distribution on walls with moderate transparency"
    }
  ]
}
