{
  "category": "body",
  "search_keywords": [
    "point",
    "delete",
    "building-blocks"
  ],
  "description": "Delete points. This operation will also delete all blocks attached to the deleted points. If < range > is not supplied, all points (and blocks) will be deleted from the current set.",
  "notes": [
    "Requires a current building-blocks set: run 'building-blocks set create <name>' then 'building-blocks set select <name>' before any block/edge/face/point operation; otherwise FLAC rejects the command with 'Unused extra parameter'."
  ],
  "python_sdk_alternative": {
    "available": false
  },
  "versions": {
    "9.0": {
      "command": "building-blocks point delete",
      "syntax": "building-blocks point delete [range]",
      "keywords": []
    }
  }
}
